a_pandas_ex_column_reduce/LICENSE
a_pandas_ex_column_reduce/README.MD
a_pandas_ex_column_reduce/__init__.py
a_pandas_ex_column_reduce/requirements.txt
a_pandas_ex_column_reduce/thirdparty.json
a_pandas_ex_column_reduce-0.10.dist-info/LICENSE.rst
a_pandas_ex_column_reduce-0.10.dist-info/METADATA
a_pandas_ex_column_reduce-0.10.dist-info/WHEEL
a_pandas_ex_column_reduce-0.10.dist-info/top_level.txt
a_pandas_ex_column_reduce-0.10.dist-info/RECORD
